wesamoyo/__init__.py
wesamoyo/configuration_wesamoyo.py
wesamoyo/modeling_wesamoyo.py
wesamoyo-1.0.7.dist-info/METADATA
wesamoyo-1.0.7.dist-info/WHEEL
wesamoyo-1.0.7.dist-info/top_level.txt
wesamoyo-1.0.7.dist-info/RECORD
