Metadata-Version: 2.4
Name: wesamoyo
Version: 1.0.7
Summary: Official SDK for Wesamoyo-293M-MoE: 293M parameter Mixture-of-Experts transformer
Home-page: https://github.com/houndtidlabs
Author: Houndtid Labs
Author-email: houndtidai@gmail.com
Classifier: Development Status :: 4 - Beta
Classifier: Intended Audience :: Developers
Classifier: Intended Audience :: Science/Research
Classifier: Topic :: Scientific/Engineering :: Artificial Intelligence
Classifier: License :: OSI Approved :: Apache Software License
Classifier: Programming Language :: Python :: 3
Classifier: Programming Language :: Python :: 3.8
Classifier: Programming Language :: Python :: 3.9
Classifier: Programming Language :: Python :: 3.10
Classifier: Programming Language :: Python :: 3.11
Classifier: Programming Language :: Python :: 3.12
Requires-Python: >=3.8
Requires-Dist: transformers>=4.40.0
Requires-Dist: torch>=2.4.1
Requires-Dist: safetensors>=0.4.5
Dynamic: author
Dynamic: author-email
Dynamic: classifier
Dynamic: description
Dynamic: description-content-type
Dynamic: home-page
Dynamic: requires-dist
Dynamic: requires-python
Dynamic: summary
